odoo/addons/donation_recurring/README.rst
odoo/addons/donation_recurring/__init__.py
odoo/addons/donation_recurring/__manifest__.py
odoo/addons/donation_recurring/demo/donation_recurring_demo.xml
odoo/addons/donation_recurring/i18n/donation_recurring.pot
odoo/addons/donation_recurring/i18n/fr.po
odoo/addons/donation_recurring/models/__init__.py
odoo/addons/donation_recurring/models/donation.py
odoo/addons/donation_recurring/static/description/icon.png
odoo/addons/donation_recurring/tests/__init__.py
odoo/addons/donation_recurring/tests/test_recurring_donations.py
odoo/addons/donation_recurring/views/donation.xml
odoo/addons/donation_recurring/wizard/__init__.py
odoo/addons/donation_recurring/wizard/donation_recurring_generate.py
odoo/addons/donation_recurring/wizard/donation_recurring_generate_view.xml
odoo11_addon_donation_recurring-11.0.1.0.0.dist-info/METADATA
odoo11_addon_donation_recurring-11.0.1.0.0.dist-info/RECORD
odoo11_addon_donation_recurring-11.0.1.0.0.dist-info/WHEEL
odoo11_addon_donation_recurring-11.0.1.0.0.dist-info/top_level.txt
